chemtensor-0.1.3.dist-info/RECORD
chemtensor-0.1.3.dist-info/WHEEL
chemtensor-0.1.3.dist-info/METADATA
chemtensor-0.1.3.dist-info/licenses/LICENSE
chemtensor/chemtensor_pymodule.dylib
chemtensor/_version.py
chemtensor/__init__.py
chemtensor/.dylibs/libhdf5.310.5.1.dylib
chemtensor/.dylibs/libaec.0.1.3.dylib
chemtensor/.dylibs/libsz.2.0.1.dylib
