Metadata-Version: 2.2
Name: chemtensor
Version: 0.1.3
Author-Email: "Christian B. Mendl" <christian.b.mendl@gmail.com>
License:                                  Apache License
Project-URL: homepage, https://github.com/qc-tum/chemtensor
Project-URL: repository, https://github.com/qc-tum/chemtensor
Project-URL: issues, https://github.com/qc-tum/chemtensor/issues
Requires-Python: >=3.8
Requires-Dist: numpy
Provides-Extra: doc
Requires-Dist: ipykernel; extra == "doc"
Requires-Dist: nbsphinx; extra == "doc"
Requires-Dist: nbsphinx-link; extra == "doc"
Requires-Dist: breathe; extra == "doc"
Requires-Dist: furo; extra == "doc"
Provides-Extra: examples
Requires-Dist: pyscf; extra == "examples"
